mindtrace/datalake/__init__.py
mindtrace/datalake/datalake.py
mindtrace/datalake/types.py
mindtrace_datalake-0.8.0.dist-info/licenses/LICENSE
mindtrace_datalake-0.8.0.dist-info/METADATA
mindtrace_datalake-0.8.0.dist-info/WHEEL
mindtrace_datalake-0.8.0.dist-info/top_level.txt
mindtrace_datalake-0.8.0.dist-info/RECORD
