Metadata-Version: 2.4
Name: mindtrace-datalake
Version: 0.8.0
Summary: Datalake functionality for Mindtrace
Author: Mindtrace Team
License-Expression: Apache-2.0
Project-URL: Homepage, https://mindtrace.ai
Project-URL: Repository, https://github.com/mindtrace/mindtrace/blob/main/mindtrace/datalake
Classifier: Programming Language :: Python :: 3
Classifier: Programming Language :: Python :: 3.12
License-File: LICENSE
Requires-Dist: mindtrace-core>=0.8.0
Requires-Dist: mindtrace-registry>=0.8.0
Requires-Dist: mindtrace-database>=0.8.0
Requires-Dist: mindtrace-services>=0.8.0
Dynamic: license-file
